jaycob_probability/Binomialdistribution.py
jaycob_probability/Gaussiandistribution.py
jaycob_probability/Generaldistribution.py
jaycob_probability/__init__.py
jaycob_probability-0.1.dist-info/DESCRIPTION.rst
jaycob_probability-0.1.dist-info/METADATA
jaycob_probability-0.1.dist-info/RECORD
jaycob_probability-0.1.dist-info/WHEEL
jaycob_probability-0.1.dist-info/metadata.json
jaycob_probability-0.1.dist-info/top_level.txt
