Metadata-Version: 2.0
Name: jaycob-probability
Version: 0.1
Summary: Gaussian distributions
Home-page: UNKNOWN
Author: Jaycob Clavel
Author-email: jaycobclavel101@gmail.com
License: UNKNOWN
Platform: UNKNOWN
